{
    "string":[
        {
            "name":"confirm_button",
            "value":"Згода",
            "attr":{
                "priority":"translate"
            }
        },
        {
            "name":"ni_notify_title",
            "value":"Запит на доступ до даних про розташування",
            "attr":{
                "priority":"translate"
            }
        },
        {
            "name":"cancel_button",
            "value":"Скасувати",
            "attr":{
                "priority":"translate"
            }
        }
    ]
}